README.md
setup.cfg
setup.py
nawano/__init__.py
nawano/cli.py
nawano/db.py
nawano/exceptions.py
nawano/settings.py
nawano/status.py
nawano/task.py
nawano/utils.py
nawano/validators.py
nawano.egg-info/PKG-INFO
nawano.egg-info/SOURCES.txt
nawano.egg-info/dependency_links.txt
nawano.egg-info/entry_points.txt
nawano.egg-info/requires.txt
nawano.egg-info/top_level.txt
nawano/clients/__init__.py
nawano/clients/rpc.py
nawano/commands/__init__.py
nawano/commands/account.py
nawano/commands/alias.py
nawano/commands/config.py
nawano/commands/funds.py
nawano/commands/root.py
nawano/commands/wallet.py
nawano/models/__init__.py
nawano/models/_base.py
nawano/models/account.py
nawano/models/alias.py
nawano/models/config.py
nawano/models/rep.py
nawano/models/state.py
nawano/models/wallet.py
nawano/repl/__init__.py
nawano/repl/completer.py
nawano/repl/completion.py
nawano/repl/loop.py
nawano/services/__init__.py
nawano/services/_base.py
nawano/services/account.py
nawano/services/alias.py
nawano/services/block.py
nawano/services/config.py
nawano/services/rep.py
nawano/services/state.py
nawano/services/wallet.py