Metadata-Version: 1.2
Name: nawano
Version: 0.1.6
Summary: Nano REPL CLI
Home-page: https://github.com/rbw/nawano
Author: Robert Wikman
Author-email: rbw@vault13.org
Maintainer: Robert Wikman
Maintainer-email: rbw@vault13.org
License: BSD-2-Clause
Download-URL: https://github.com/rbw/nawano/tarball/0.1.6
Keywords: nano,cryptocurrency,cli,wallet
Platform: any
Classifier: Topic :: Utilities
Classifier: Operating System :: OS Independent
Classifier: Programming Language :: Python
Classifier: Topic :: Software Development :: Libraries :: Python Modules
Requires-Python: >=3.6
